redis_semaphore
tests
