Metadata-Version: 1.1
Name: Redis-Semaphore
Version: 0.2.1
Summary: A distributed semaphore and mutex built on Redis.
Home-page: https://github.com/bluele/redis-semaphore
Author: bluele
Author-email: jksmphone@gmail.com
License: MIT
Keywords: redis semaphore
Platform: UNKNOWN
Classifier: Development Status :: 4 - Beta
Classifier: License :: OSI Approved :: MIT License
Classifier: Programming Language :: Python
Classifier: Programming Language :: Python :: 2
Classifier: Programming Language :: Python :: 2.7
Classifier: Programming Language :: Python :: 3.3
Classifier: Programming Language :: Python :: 3.4
Classifier: Programming Language :: Python :: 3.5
